[{"subjectId": "CLASSIC", "number": "10A", "subjectShort": "CLASSIC", "displayTitle": "10A - Intro Greek Civ", "description": null, "hasTopics": false, "title": "Intro Greek Civ", "topic": null, "subject": "Classics", "id": "CLASSIC|10A", "titleLong": "Classics 10A - Intro Greek Civ"}, {"subjectId": "CLASSIC", "number": "17A", "subjectShort": "CLASSIC", "displayTitle": "17A - Elem Greek Arch", "description": null, "hasTopics": false, "title": "Elem Greek Arch", "topic": null, "subject": "Classics", "id": "CLASSIC|17A", "titleLong": "Classics 17A - Elem Greek Arch"}, {"subjectId": "CLASSIC", "number": "24", "subjectShort": "CLASSIC", "displayTitle": "24 - Freshman Seminars", "description": null, "hasTopics": false, "title": "Freshman Seminars", "topic": null, "subject": "Classics", "id": "CLASSIC|24", "titleLong": "Classics 24 - Freshman Seminars"}, {"subjectId": "CLASSIC", "number": "36", "subjectShort": "CLASSIC", "displayTitle": "36 - Greek Philosophy", "description": null, "hasTopics": false, "title": "Greek Philosophy", "topic": null, "subject": "Classics", "id": "CLASSIC|36", "titleLong": "Classics 36 - Greek Philosophy"}, {"subjectId": "CLASSIC", "number": "130", "subjectShort": "CLASSIC", "displayTitle": "130 - Topics", "description": null, "hasTopics": false, "title": "Topics", "topic": null, "subject": "Classics", "id": "CLASSIC|130", "titleLong": "Classics 130 - Topics"}, {"subjectId": "CLASSIC", "number": "163", "subjectShort": "CLASSIC", "displayTitle": "163 - Topic Greek Philos", "description": null, "hasTopics": false, "title": "Topic Greek Philos", "topic": null, "subject": "Classics", "id": "CLASSIC|163", "titleLong": "Classics 163 - Topic Greek Philos"}, {"subjectId": "CLASSIC", "number": "200", "subjectShort": "CLASSIC", "displayTitle": "200 - Proseminar", "description": null, "hasTopics": false, "title": "Proseminar", "topic": null, "subject": "Classics", "id": "CLASSIC|200", "titleLong": "Classics 200 - Proseminar"}, {"subjectId": "CLASSIC", "number": "202A", "subjectShort": "CLASSIC", "displayTitle": "202A - Survey Latin Lit", "description": null, "hasTopics": false, "title": "Survey Latin Lit", "topic": null, "subject": "Classics", "id": "CLASSIC|202A", "titleLong": "Classics 202A - Survey Latin Lit"}, {"subjectId": "CLASSIC", "number": "211", "subjectShort": "CLASSIC", "displayTitle": "211 - Archaic Grk Poetry", "description": null, "hasTopics": false, "title": "Archaic Grk Poetry", "topic": null, "subject": "Classics", "id": "CLASSIC|211", "titleLong": "Classics 211 - Archaic Grk Poetry"}, {"subjectId": "CLASSIC", "number": "220A", "subjectShort": "CLASSIC", "displayTitle": "220A - Gk And Lat Epigr", "description": null, "hasTopics": false, "title": "Gk And Lat Epigr", "topic": null, "subject": "Classics", "id": "CLASSIC|220A", "titleLong": "Classics 220A - Gk And Lat Epigr"}, {"subjectId": "CLASSIC", "number": "250", "subjectShort": "CLASSIC", "displayTitle": "250 - Adv Greek Comp", "description": null, "hasTopics": false, "title": "Adv Greek Comp", "topic": null, "subject": "Classics", "id": "CLASSIC|250", "titleLong": "Classics 250 - Adv Greek Comp"}, {"subjectId": "CLASSIC", "number": "270", "subjectShort": "CLASSIC", "displayTitle": "270 - Seminar Class Arch", "description": null, "hasTopics": false, "title": "Seminar Class Arch", "topic": null, "subject": "Classics", "id": "CLASSIC|270", "titleLong": "Classics 270 - Seminar Class Arch"}, {"subjectId": "CLASSIC", "number": "302", "subjectShort": "CLASSIC", "displayTitle": "302 - Teaching Practicum", "description": null, "hasTopics": false, "title": "Teaching Practicum", "topic": null, "subject": "Classics", "id": "CLASSIC|302", "titleLong": "Classics 302 - Teaching Practicum"}, {"subjectId": "CLASSIC", "number": "375", "subjectShort": "CLASSIC", "displayTitle": "375 - Teaching Methods", "description": null, "hasTopics": false, "title": "Teaching Methods", "topic": null, "subject": "Classics", "id": "CLASSIC|375", "titleLong": "Classics 375 - Teaching Methods"}, {"subjectId": "CLASSIC", "number": "R44", "subjectShort": "CLASSIC", "displayTitle": "R44 - Roots Western Civ", "description": null, "hasTopics": false, "title": "Roots Western Civ", "topic": null, "subject": "Classics", "id": "CLASSIC|R44", "titleLong": "Classics R44 - Roots Western Civ"}]