[{"subjectId": "SASIAN", "number": "1A", "subjectShort": "S ASIAN", "displayTitle": "1A - Civ Early India", "description": null, "hasTopics": false, "title": "Civ Early India", "topic": null, "subject": "South Asian", "id": "SASIAN|1A", "titleLong": "South Asian 1A - Civ Early India"}, {"subjectId": "SASIAN", "number": "128", "subjectShort": "S ASIAN", "displayTitle": "128 - Rel Mvmts Mod India", "description": null, "hasTopics": false, "title": "Rel Mvmts Mod India", "topic": null, "subject": "South Asian", "id": "SASIAN|128", "titleLong": "South Asian 128 - Rel Mvmts Mod India"}, {"subjectId": "SASIAN", "number": "140", "subjectShort": "S ASIAN", "displayTitle": "140 - Hindu Mythology", "description": null, "hasTopics": false, "title": "Hindu Mythology", "topic": null, "subject": "South Asian", "id": "SASIAN|140", "titleLong": "South Asian 140 - Hindu Mythology"}, {"subjectId": "SASIAN", "number": "C114", "subjectShort": "S ASIAN", "displayTitle": "C114 - Tibetan Buddhism", "description": null, "hasTopics": false, "title": "Tibetan Buddhism", "topic": null, "subject": "South Asian", "id": "SASIAN|C114", "titleLong": "South Asian C114 - Tibetan Buddhism"}, {"subjectId": "SASIAN", "number": "C215", "subjectShort": "S ASIAN", "displayTitle": "C215 - Indian Buddhst Text", "description": null, "hasTopics": false, "title": "Indian Buddhst Text", "topic": null, "subject": "South Asian", "id": "SASIAN|C215", "titleLong": "South Asian C215 - Indian Buddhst Text"}, {"subjectId": "SASIAN", "number": "C224", "subjectShort": "S ASIAN", "displayTitle": "C224 - Tibetan Bddhst Txts", "description": null, "hasTopics": false, "title": "Tibetan Bddhst Txts", "topic": null, "subject": "South Asian", "id": "SASIAN|C224", "titleLong": "South Asian C224 - Tibetan Bddhst Txts"}, {"subjectId": "SASIAN", "number": "R5A", "subjectShort": "S ASIAN", "displayTitle": "R5A - Great Books India", "description": null, "hasTopics": false, "title": "Great Books India", "topic": null, "subject": "South Asian", "id": "SASIAN|R5A", "titleLong": "South Asian R5A - Great Books India"}]